LICENSE.txt
README.md
setup.cfg
setup.py
Deepak_102003483.egg-info/PKG-INFO
Deepak_102003483.egg-info/SOURCES.txt
Deepak_102003483.egg-info/dependency_links.txt
Deepak_102003483.egg-info/entry_points.txt
Deepak_102003483.egg-info/requires.txt
Deepak_102003483.egg-info/top_level.txt
Topsis/102003483.py