Metadata-Version: 2.1
Name: Deepak-102003483
Version: 1.1.10
Summary: Topsis Package
Author: Deepak Aggarwal
Author-email: <daggarwal2_be20@thapar.edu>
License: MIT License
Keywords: python,topsis,mcdm
Classifier: Development Status :: 1 - Planning
Classifier: Intended Audience :: Developers
Classifier: Programming Language :: Python :: 3
Classifier: Operating System :: Unix
Classifier: Operating System :: MacOS :: MacOS X
Classifier: Operating System :: Microsoft :: Windows
License-File: LICENSE.txt
